pylontech/__init__.py
pylontech/pylontech.py
python_pylontech-0.3.3.dist-info/LICENSE
python_pylontech-0.3.3.dist-info/METADATA
python_pylontech-0.3.3.dist-info/WHEEL
python_pylontech-0.3.3.dist-info/top_level.txt
python_pylontech-0.3.3.dist-info/RECORD
