Metadata-Version: 2.1
Name: python-pylontech
Version: 0.3.3
Summary: Interfaces with Pylontech Batteries using RS485 protocol
Home-page: http://github.com/Frankkkkk/python-pylontech
Author: Frank Villaro-Dixon
Author-email: frank@villaro-dixon.eu
License: MIT
Keywords: pylontech pylon rs485 lithium battery US2000 US2000C US3000
Classifier: Development Status :: 3 - Alpha
Classifier: Topic :: Utilities
Classifier: License :: OSI Approved :: MIT License
License-File: LICENSE
Requires-Dist: pyserial
Requires-Dist: construct
